
[
    {
        "id": "agama-sma-1",
        "question": "Hukum melaksanakan shalat Jumat bagi laki-laki muslim adalah...",
        "options": {
            "A": {"text": "Sunnah", "description": "Dianjurkan tapi tidak wajib"},
            "B": {"text": "Fardhu 'Ain", "description": "Wajib bagi setiap individu"},
            "C": {"text": "Fardhu Kifayah", "description": "Wajib bagi sebagian masyarakat"},
            "D": {"text": "Mubah", "description": "Boleh dilakukan atau tidak"}
        },
        "correctAnswer": "B",
        "difficulty": "sedang",
        "explanation": "Shalat Jumat hukumnya fardhu 'ain (wajib) bagi setiap muslim laki-laki yang sudah baligh, berakal, dan tidak ada uzur syar'i."
    }
]
